adobe/__init__.py
adobe/auth.py
adobe/client.py
adobe/constants.py
adobe/conversion.py
adobe/cookie_manager.py
adobe/download.py
adobe/exceptions.py
adobe/models.py
adobe/rate_limiter.py
adobe/session_cycling.py
adobe/upload.py
adobe/urls.py
adobe/usage_tracker.py
adobe/utils.py
adobe/cli/__init__.py
adobe/cli/api_discovery_helper.py
adobe_helper-1.1.2.dist-info/METADATA
adobe_helper-1.1.2.dist-info/WHEEL
adobe_helper-1.1.2.dist-info/entry_points.txt
adobe_helper-1.1.2.dist-info/licenses/LICENSE
adobe_helper-1.1.2.dist-info/RECORD
