Metadata-Version: 2.4
Name: adobe-helper
Version: 1.1.2
Summary: Python client for Adobe PDF to Word conversion using Adobe's online services
Project-URL: Homepage, https://github.com/karlorz/adobe-helper
Project-URL: Documentation, https://github.com/karlorz/adobe-helper/blob/main/README.md
Project-URL: Repository, https://github.com/karlorz/adobe-helper
Project-URL: Issues, https://github.com/karlorz/adobe-helper/issues
Author-email: Adobe Helper Contributors <adobe-helper@example.com>
License: Apache License
License-File: LICENSE
Keywords: adobe,api,async,conversion,docx,httpx,pdf,word
Classifier: Development Status :: 3 - Alpha
Classifier: Intended Audience :: Developers
Classifier: License :: OSI Approved :: MIT License
Classifier: Programming Language :: Python :: 3
Classifier: Programming Language :: Python :: 3.11
Classifier: Programming Language :: Python :: 3.12
Classifier: Programming Language :: Python :: 3.13
Classifier: Topic :: Office/Business
Classifier: Topic :: Software Development :: Libraries :: Python Modules
Requires-Python: >=3.11
Requires-Dist: click>=8.1.0
Requires-Dist: httpx[http2]>=0.27.0
Requires-Dist: pydantic>=2.0.0
Requires-Dist: python-dotenv>=1.0.0
Requires-Dist: rich>=13.0.0
Provides-Extra: browser
Requires-Dist: playwright>=1.40.0; extra == 'browser'
